CHANGES.txt
COPYRIGHT.txt
LICENSE.txt
README.txt
TODO.txt
bootstrap.py
buildout.cfg
setup.py
src/hurry/__init__.py
src/hurry.resource.egg-info/PKG-INFO
src/hurry.resource.egg-info/SOURCES.txt
src/hurry.resource.egg-info/dependency_links.txt
src/hurry.resource.egg-info/namespace_packages.txt
src/hurry.resource.egg-info/not-zip-safe
src/hurry.resource.egg-info/requires.txt
src/hurry.resource.egg-info/top_level.txt
src/hurry/resource/README.txt
src/hurry/resource/__init__.py
src/hurry/resource/core.py
src/hurry/resource/interfaces.py
src/hurry/resource/tests.py
src/hurry/resource/wsgi.py
src/hurry/resource/zca.py