Metadata-Version: 1.0
Name: hurry.resource
Version: 0.10
Summary: Flexible resources for web applications.
Home-page: http://pypi.python.org/pypi/hurry.resource
Author: Martijn Faassen
Author-email: faassen@startifact.com
License: ZPL 2.1
Platform: UNKNOWN
